mermaid_parser/__init__.py
mermaid_parser/converters/__init__.py
mermaid_parser/converters/flowchart.py
mermaid_parser/converters/state_diagram.py
mermaid_parser/js/package-lock.json
mermaid_parser/js/package.json
mermaid_parser/js/parser.bundle.js
mermaid_parser/js/parser.mjs
mermaid_parser/js/rollup.config.mjs
mermaid_parser/parser.py
mermaid_parser/structs/state_diagram.py
mermaid_parser_py-0.0.3.dist-info/LICENSE
mermaid_parser_py-0.0.3.dist-info/METADATA
mermaid_parser_py-0.0.3.dist-info/WHEEL
mermaid_parser_py-0.0.3.dist-info/RECORD
