Metadata-Version: 2.3
Name: mermaid-parser-py
Version: 0.0.3
Summary: Parse Mermaid into manipulable Python objects
License: MIT
Author: Boqi Chen
Author-email: boqi.chen@mail.mcgill.ca
Requires-Python: <4.0,>=3.11
Classifier: License :: OSI Approved :: MIT License
Classifier: Programming Language :: Python :: 3
Classifier: Programming Language :: Python :: 3.11
Classifier: Programming Language :: Python :: 3.12
Classifier: Programming Language :: Python :: 3.13
Requires-Dist: loguru (>=0.7.3,<0.8.0)
Requires-Dist: mermaid-py (>=0.8.0,<0.9.0)
Requires-Dist: networkx (>=3.5,<4.0)
Requires-Dist: pydantic (>=2.11.7,<3.0.0)
Requires-Dist: pythonmonkey (>=1.2.0,<2.0.0)
Project-URL: Homepage, https://github.com/20001LastOrder/mermaid-parser-py
